{
  "hash": "7761de2f",
  "browserHash": "5a8f9dfe",
  "optimized": {
    "@vueuse/core": {
      "src": "../../../../node_modules/@vueuse/core/index.mjs",
      "file": "@vueuse_core.js",
      "fileHash": "047f5830",
      "needsInterop": false
    },
    "@vuepress/shared": {
      "src": "../../../../node_modules/@vuepress/shared/dist/index.js",
      "file": "@vuepress_shared.js",
      "fileHash": "de2c098e",
      "needsInterop": false
    },
    "vue": {
      "src": "../../../../node_modules/vue/dist/vue.runtime.esm-bundler.js",
      "file": "vue.js",
      "fileHash": "eef078e4",
      "needsInterop": false
    },
    "vue-router": {
      "src": "../../../../node_modules/vue-router/dist/vue-router.esm-bundler.js",
      "file": "vue-router.js",
      "fileHash": "3ed5e677",
      "needsInterop": false
    }
  },
  "chunks": {
    "chunk-A535AHWC": {
      "file": "chunk-A535AHWC.js"
    },
    "chunk-NLVKWF7H": {
      "file": "chunk-NLVKWF7H.js"
    }
  }
}